torchstate/__init__.py
torchstate/C/__init__.py
torchstate/C/utils.py
torchstate-0.1.0.dist-info/LICENSE
torchstate-0.1.0.dist-info/METADATA
torchstate-0.1.0.dist-info/WHEEL
torchstate-0.1.0.dist-info/top_level.txt
torchstate-0.1.0.dist-info/RECORD
