Metadata-Version: 2.1
Name: torchstate
Version: 0.1.0
Summary: Torch state package
Home-page: https://github.com/Jackmin801/torchstate
Author: Jack Min Ong
Author-email: ongjackm@gmail.com
Classifier: Programming Language :: Python :: 3
Classifier: License :: OSI Approved :: MIT License
Classifier: Operating System :: OS Independent
Requires-Python: >=3.6
License-File: LICENSE
Requires-Dist: torch>=2.0.0
